lock_run/__init__.py
lock_run/handler_code.py
lock_run/handler_data_files.py
lock_run/main.py
lock_run/reader.py
lock_run/utilitiles.py
lock_run-0.7.0.dist-info/entry_points.txt
lock_run-0.7.0.dist-info/METADATA
lock_run-0.7.0.dist-info/WHEEL
lock_run-0.7.0.dist-info/RECORD
