Metadata-Version: 2.1
Name: lock-run
Version: 0.7.0
Summary: Python runner with cipher
License: MIT
Author: dima-on
Author-email: sinica911@gmail.com
Requires-Python: >=3.12,<4.0
Classifier: License :: OSI Approved :: MIT License
Classifier: Programming Language :: Python :: 3
Classifier: Programming Language :: Python :: 3.12
Classifier: Programming Language :: Python :: 3.13
Requires-Dist: seal-py (>=0.8.2,<0.9.0)
